dj_shop_cart/__init__.py
dj_shop_cart/apps.py
dj_shop_cart/cart.py
dj_shop_cart/conf.py
dj_shop_cart/context_processors.py
dj_shop_cart/migrations/0001_initial.py
dj_shop_cart/migrations/0002_rename_items_cart_data.py
dj_shop_cart/migrations/__init__.py
dj_shop_cart/models.py
dj_shop_cart/modifiers.py
dj_shop_cart/protocols.py
dj_shop_cart/py.typed
dj_shop_cart/storages.py
dj_shop_cart/utils.py
dj_shop_cart-8.0.1.dist-info/WHEEL
dj_shop_cart-8.0.1.dist-info/METADATA
dj_shop_cart-8.0.1.dist-info/RECORD
