Metadata-Version: 2.3
Name: dj-shop-cart
Version: 8.0.1
Summary: Simple django cart manager for your django projects.
Keywords: django,python,cart,shop,ecommerce
Author: Tobi-De
Author-email: Tobi-De <tobidegnon@proton.me>
License: MIT
Classifier: Development Status :: 5 - Production/Stable
Classifier: Programming Language :: Python
Classifier: Programming Language :: Python :: 3.10
Classifier: Programming Language :: Python :: 3.11
Classifier: Programming Language :: Python :: 3.12
Classifier: Programming Language :: Python :: 3.13
Classifier: Programming Language :: Python :: Implementation :: CPython
Classifier: Programming Language :: Python :: Implementation :: PyPy
Classifier: Framework :: Django :: 3.0
Classifier: Framework :: Django :: 3.1
Classifier: Framework :: Django :: 3.2
Classifier: Framework :: Django :: 4.0
Classifier: Framework :: Django :: 4.1
Classifier: Framework :: Django :: 4.2
Classifier: Framework :: Django :: 5.0
Classifier: Framework :: Django :: 5.2
Classifier: Intended Audience :: Developers
Classifier: Natural Language :: English
Requires-Dist: django>=5.2
Requires-Dist: attrs>=23.2.0
Requires-Python: >=3.10
Project-URL: Documentation, https://github.com/Tobi-De/dj_shop_cart#readme
Project-URL: Issues, https://github.com/Tobi-De/dj_shop_cart/issues
Project-URL: Source, https://github.com/Tobi-De/dj_shop_cart
